usman_ghani/__init__.py
usman_ghani/__main__.py
Usman_Ghani-0.1.dist-info/METADATA
Usman_Ghani-0.1.dist-info/WHEEL
Usman_Ghani-0.1.dist-info/top_level.txt
Usman_Ghani-0.1.dist-info/RECORD
