Metadata-Version: 2.1
Name: Usman-Ghani
Version: 0.1
Summary: Python installable biography of Usman Ghani
Author: Usman Ghani
License: MIT
Classifier: Programming Language :: Python :: 3
Classifier: License :: OSI Approved :: MIT License
Classifier: Operating System :: OS Independent
Requires-Python: >=3.6
